aiohealthcheck.py
aiohealthcheck-2018.7.1.dist-info/LICENSE
aiohealthcheck-2018.7.1.dist-info/WHEEL
aiohealthcheck-2018.7.1.dist-info/METADATA
aiohealthcheck-2018.7.1.dist-info/RECORD
