Metadata-Version: 2.1
Name: aiohealthcheck
Version: 2018.7.1
Summary: aiohealthcheck: super-simple TCP health-check endpoint
Home-page: https://github.com/cjrh/aiohealthcheck
License: UNKNOWN
Author: Caleb Hattingh
Author-email: caleb.hattingh@gmail.com
Classifier: License :: OSI Approved :: Apache Software License
Classifier: Natural Language :: English
Classifier: Programming Language :: Python
Classifier: Programming Language :: Python :: 3.5
Classifier: Programming Language :: Python :: 3.6
Classifier: Programming Language :: Python :: 3.7
Classifier: Operating System :: OS Independent
